claude_kb/cli.py
claude_kb/config.py
claude_kb/db.py
claude_kb/formatters.py
claude_kb/import_claude.py
claude_kb/mcp.py
claude_kb/models.py
claude_kb/search.py
claude_kb-0.5.0.dist-info/METADATA
claude_kb-0.5.0.dist-info/WHEEL
claude_kb-0.5.0.dist-info/entry_points.txt
claude_kb-0.5.0.dist-info/licenses/LICENSE
claude_kb-0.5.0.dist-info/RECORD
