Metadata-Version: 2.4
Name: claude-kb
Version: 0.5.0
Summary: Universal knowledge base with Qdrant for Claude Code integration
Project-URL: Homepage, https://github.com/tenequm/claude-kb
Project-URL: Repository, https://github.com/tenequm/claude-kb
Project-URL: Issues, https://github.com/tenequm/claude-kb/issues
Author-email: Misha Kolesnik <misha@kolesnik.io>
License: MIT
License-File: LICENSE
Keywords: ai,claude,embeddings,knowledge-base,qdrant,semantic-search,vector-search
Classifier: Development Status :: 3 - Alpha
Classifier: Environment :: Console
Classifier: Intended Audience :: Developers
Classifier: License :: OSI Approved :: MIT License
Classifier: Operating System :: OS Independent
Classifier: Programming Language :: Python :: 3
Classifier: Programming Language :: Python :: 3.13
Classifier: Topic :: Database
Classifier: Topic :: Text Processing :: Indexing
Requires-Python: >=3.13
Requires-Dist: click<9,>=8.1.0
Requires-Dist: httpx<1,>=0.27.0
Requires-Dist: mcp<2,>=1.23.0
Requires-Dist: pydantic<3,>=2.0.0
Requires-Dist: python-dotenv<2,>=1.0.0
Requires-Dist: qdrant-client<2,>=1.11.0
Requires-Dist: rich<15,>=13.0.0
Requires-Dist: sentence-transformers<6,>=5.0.0
Requires-Dist: tiktoken<1,>=0.5.0
Requires-Dist: torch<3,>=2.0.0
